{
  "button": {
    "path": "/micro/components/file/button/button-1749918964178.js",
    "time": "1749918964178",
    "version": "0.0.4",
    "publishInfo": {
      "publisher": "szy",
      "publishTime": "1749918964178",
      "description": "Version 0.0.4",
      "buildInfo": "$npm_config_buildInfo",
      "status": "published"
    },
    "buildDetails": {
      "componentName": "button",
      "version": "0.0.4",
      "buildTime": "2025/6/15 上午12:35:11",
      "gitCommit": "9388f48e062108677e004d750924d365c81d2262",
      "gitBranch": "master",
      "buildInfo": "$npm_config_buildInfo"
    },
    "metadata": {
      "name": "@zxz-ui/button",
      "dependencies": {},
      "peerDependencies": {
        "react": "^16.13.1",
        "react-dom": "^16.13.1"
      },
      "author": "zxz",
      "license": "ISC",
      "repository": {
        "type": "git",
        "url": ""
      }
    }
  },
  "card": {
    "path": "/micro/components/file/card/card-1748879130268.js",
    "time": "1748879130268",
    "version": "0.0.1",
    "publishInfo": {
      "publisher": "szy",
      "publishTime": "1748879130268",
      "description": "Version 0.0.1",
      "buildInfo": "$npm_config_buildInfo",
      "status": "published"
    },
    "buildDetails": {
      "componentName": "card",
      "version": "0.0.1",
      "buildTime": "2025-06-02 23:45:22",
      "gitCommit": "208ead90ec29d28dd39775148b62f489209c9f4e",
      "gitBranch": "master",
      "buildInfo": "$npm_config_buildInfo"
    },
    "metadata": {
      "name": "@zxz-ui/card",
      "dependencies": {},
      "peerDependencies": {
        "react": "^16.13.1",
        "react-dom": "^16.13.1"
      },
      "author": "zxz",
      "license": "ISC",
      "repository": {
        "type": "git",
        "url": ""
      }
    }
  }
}